mrftools/__init__.py
mrftools/dictionaryParameters.py
mrftools/reconstructionParameters.py
mrftools/sequenceParameters.py
mrftools/simulationParameters.py
mrftools/trajectoryParameters.py
mrftools/ReconstructionModules/CacheModule.py
mrftools/ReconstructionModules/CoilCombinationModule.py
mrftools/ReconstructionModules/CoilCompressionModule.py
mrftools/ReconstructionModules/CoilwiseNoisefloorMaskingModule.py
mrftools/ReconstructionModules/DataSubsetModule.py
mrftools/ReconstructionModules/IFFTModule.py
mrftools/ReconstructionModules/IterativeNUFFTModule.py
mrftools/ReconstructionModules/IterativeRadialMaskingModule.py
mrftools/ReconstructionModules/NUFFTModule.py
mrftools/ReconstructionModules/PatternMatchingModule.py
mrftools/ReconstructionModules/RecallModule.py
mrftools/ReconstructionModules/ReconstructionModule.py
mrftools/ReconstructionModules/SVDCompressionModule.py
mrftools/ReconstructionModules/ScalingModule.py
mrftools/ReconstructionModules/__init__.py
mrftools/SequenceModules/AcquisitionModule.py
mrftools/SequenceModules/DeadtimeRecoveryModule.py
mrftools/SequenceModules/FISPAcquisitionModule.py
mrftools/SequenceModules/GradientPreparationModule.py
mrftools/SequenceModules/InversionModule.py
mrftools/SequenceModules/PreparationModule.py
mrftools/SequenceModules/RFPreparationModule.py
mrftools/SequenceModules/RecoveryModule.py
mrftools/SequenceModules/SequenceModule.py
mrftools/SequenceModules/SpoilerModule.py
mrftools/SequenceModules/T2PreparationModule.py
mrftools/SequenceModules/TRUEFISPAcquisitionModule.py
mrftools/SequenceModules/__init__.py
mrftools/Types/__init__.py
mrftools/Types/dataStructs.py
mrftools/Types/sequenceUnits.py
mrftools/Types/trajectoryUnits.py
mrftools/Types/types.py
mrftools/Types/units.py
mrftools/Utilities/__init__.py
mrftools/Utilities/ismrmrd.py
mrftools/Utilities/sequenceConverters.py
mrftools/Utilities/sequenceGenerators.py
mrftools/Utilities/tensors.py
mrftools/Utilities/twixReader.py
mrftools/Utilities/visualization.py
mrftools-0.2.12.dist-info/LICENSE
mrftools-0.2.12.dist-info/METADATA
mrftools-0.2.12.dist-info/WHEEL
mrftools-0.2.12.dist-info/top_level.txt
mrftools-0.2.12.dist-info/RECORD
