Metadata-Version: 2.1
Name: mrftools
Version: 0.2.12
Summary: Tools for Magnetic Resonance Fingerprinting
Home-page: https://gitlab.casemri.com/common-resources/mrftools
Author: Andrew Dupuis
Author-email: andrew.dupuis@case.edu
License: PLEASE READ THESE TERMS CAREFULLY BEFORE USING THIS SOFTWARE AND DATA. IF YOU DO NOT AGREE TO THESE TERMS, DO NOT USE THE SOFTWARE OR DATA AND DELETE ANY MATERIAL ALREADY DOWNLOADED OR ACCESSED. BY CONTINUING, YOU REPRESENT THAT YOU HAVE THE AUTHORITY TO BIND YOUR ORGANIZATION AND THAT YOU ASSENT TO THE BELOW AGREEMENT.
Platform: UNKNOWN
Classifier: Programming Language :: Python :: 3
Classifier: Operating System :: OS Independent
License-File: LICENSE
Requires-Dist: SimpleITK (>=2.2.0)
Requires-Dist: cxxheaderparser
Requires-Dist: h5py (>=3.7.0)
Requires-Dist: ismrmrd (>=1.12.3)
Requires-Dist: jsonpickle (>=3.0.1)
Requires-Dist: kornia (>=0.6.8)
Requires-Dist: matplotlib (>=3.5.0)
Requires-Dist: nibabel (>=4.0.0)
Requires-Dist: numpy (>=1.25.0)
Requires-Dist: ptwt (>=0.1.6)
Requires-Dist: scipy (>=1.10.0)
Requires-Dist: torch (>=1.13.0)
Requires-Dist: tqdm (>=4.62.3)
